{
  "last_saved_link": {
    "_sicong": "https://www.instagram.com/p/BzC_PrkpNHs/",
    "chiling.lin": "https://www.instagram.com/p/BzIv3GtBvOk/",
    "gal_gadot": "https://www.instagram.com/p/BzE26xyBAAO/",
    "jaychou": "https://www.instagram.com/p/BzHqIcynL2N/",
    "langlangpiano": "https://www.instagram.com/p/BzGYDfvlu-E/",
    "showlo": "https://www.instagram.com/p/BzHagp-pvgl/",
    "tanaka_tatsuya": "https://www.instagram.com/p/BzCFlKjDHPd/",
    "tfboys_karry_921": "https://www.instagram.com/p/BZ32EsZFa-7/"
  }
}